dataVisualization/Circos.py
dataVisualization/Marimekko.py
dataVisualization/Organogram.py
dataVisualization/README.md
dataVisualization/Unilever.png
dataVisualization/__init__.py
dataVisualization/bars.py
dataVisualization/exceptions.py
dataVisualization/fig1.html
dataVisualization/fig1.png
dataVisualization/heatmap.py
dataVisualization/images.zip
dataVisualization/label_formatter.py
dataVisualization/legends.py
dataVisualization/line_trials.py
dataVisualization/log-bar.py
dataVisualization/main.py
dataVisualization/new_sankey.py
dataVisualization/orgchart.png
dataVisualization/pies.py
dataVisualization/pyproject.toml
dataVisualization/result.png
dataVisualization/sankey.py
dataVisualization/sankey_trials.py
dataVisualization/susmon_colours.py
dataVisualization/time_series.py
dataVisualization/tree_legend.svg
dataVisualization/treemap.py
dataVisualization/vis_scripts.py
dataVisualization/images/1.svg
dataVisualization/images/10.svg
dataVisualization/images/11.svg
dataVisualization/images/12.svg
dataVisualization/images/13.svg
dataVisualization/images/14.svg
dataVisualization/images/15.svg
dataVisualization/images/16.svg
dataVisualization/images/17.svg
dataVisualization/images/18.svg
dataVisualization/images/19.svg
dataVisualization/images/2.svg
dataVisualization/images/20.svg
dataVisualization/images/21.svg
dataVisualization/images/22.svg
dataVisualization/images/23.svg
dataVisualization/images/24.svg
dataVisualization/images/25.svg
dataVisualization/images/26.svg
dataVisualization/images/27.svg
dataVisualization/images/28.svg
dataVisualization/images/29.svg
dataVisualization/images/3.svg
dataVisualization/images/30.svg
dataVisualization/images/31.svg
dataVisualization/images/32.svg
dataVisualization/images/33.svg
dataVisualization/images/34.svg
dataVisualization/images/35.svg
dataVisualization/images/36.svg
dataVisualization/images/37.svg
dataVisualization/images/38.svg
dataVisualization/images/39.svg
dataVisualization/images/4.svg
dataVisualization/images/40.svg
datavisualization-1.36.dist-info/METADATA
datavisualization-1.36.dist-info/WHEEL
datavisualization-1.36.dist-info/RECORD
