Metadata-Version: 2.3
Name: dataVisualization
Version: 1.36
Project-URL: Homepage, https://gitlab.com/susmon/data-visualization
Project-URL: Bug Tracker, https://gitlab.com/susmon/data-visualization/issues
Author-email: Ethan Price <ethan@susmon.com>
Classifier: License :: OSI Approved :: MIT License
Classifier: Operating System :: OS Independent
Classifier: Programming Language :: Python :: 3
Requires-Python: >=3.7
Requires-Dist: matplotlib
Requires-Dist: numpy
Requires-Dist: openpyxl
Requires-Dist: pandas
